holytools/__init__.py
holytools/abstract/__init__.py
holytools/abstract/serialization/__init__.py
holytools/abstract/serialization/dillable.py
holytools/abstract/serialization/jsondataclass.py
holytools/abstract/serialization/serializable.py
holytools/abstract/tree/__init__.py
holytools/abstract/tree/node.py
holytools/configs/__init__.py
holytools/configs/base.py
holytools/configs/configs.py
holytools/configs/cred.py
holytools/devtools/__init__.py
holytools/devtools/input.py
holytools/devtools/inspection/__init__.py
holytools/devtools/inspection/modules.py
holytools/devtools/inspection/types.py
holytools/devtools/testing/__init__.py
holytools/devtools/testing/basetest.py
holytools/devtools/testing/discovery.py
holytools/devtools/testing/result.py
holytools/devtools/testing/runner.py
holytools/devtools/testing/unit.py
holytools/events/__init__.py
holytools/events/clocks.py
holytools/events/scheduler.py
holytools/fileIO/__init__.py
holytools/fileIO/segments.py
holytools/fileIO/converters/__init__.py
holytools/fileIO/converters/bytes.py
holytools/fileIO/converters/images.py
holytools/fileIO/examples/__init__.py
holytools/fileIO/examples/file.bin
holytools/fileIO/examples/file.csv
holytools/fileIO/examples/file.jpg
holytools/fileIO/examples/file.pdf
holytools/fileIO/examples/file.png
holytools/fileIO/examples/file.txt
holytools/fileIO/examples/file.wav
holytools/fileIO/examples/provider.py
holytools/fileIO/filetypes/__init__.py
holytools/fileIO/filetypes/binary.py
holytools/fileIO/filetypes/fileio.py
holytools/fileIO/filetypes/image.py
holytools/fileIO/filetypes/plaintext.py
holytools/fsys/__init__.py
holytools/fsys/fsys_node.py
holytools/fsys/path_tools.py
holytools/fsys/resources.py
holytools/hardware/__init__.py
holytools/hardware/display/__init__.py
holytools/hardware/display/display.py
holytools/hardware/display/grid_draw.py
holytools/hardware/display/types.py
holytools/hardware/input/__init__.py
holytools/hardware/input/keyboard.py
holytools-0.9.18.dist-info/licenses/LICENSE.txt
holytools-0.9.18.dist-info/METADATA
holytools-0.9.18.dist-info/WHEEL
holytools-0.9.18.dist-info/entry_points.txt
holytools-0.9.18.dist-info/top_level.txt
holytools-0.9.18.dist-info/RECORD
