Metadata-Version: 2.4
Name: holytools
Version: 0.9.18
Summary: Collection of very general python utilities 
Author-email: Daniel Hollarek <daniel.hollarek@googlemail.com>
Project-URL: repository, https://github.com/Somerandomguy10111/holytools
License-File: LICENSE.txt
Requires-Dist: requests
Requires-Dist: pathvalidate
Requires-Dist: psutil
Requires-Dist: pympler
Requires-Dist: dill
Requires-Dist: orjson
Requires-Dist: mss
Requires-Dist: screeninfo
Requires-Dist: pynput
Requires-Dist: pillow
Requires-Dist: progressbar2
Requires-Dist: tabulate
Requires-Dist: cryptoalgos
Requires-Dist: secretstorage
Provides-Extra: test
Requires-Dist: flask; extra == "test"
Dynamic: license-file
